README.md
setup.py
cv2_utils/__init__.py
cv2_utils/sequential.py
cv2_utils/utils.py
cv2_utils/video_capture.py
cv2_utils.egg-info/PKG-INFO
cv2_utils.egg-info/SOURCES.txt
cv2_utils.egg-info/dependency_links.txt
cv2_utils.egg-info/top_level.txt
cv2_utils/layers/__init__.py
cv2_utils/layers/basic_layer.py
cv2_utils/layers/detector/__init__.py
cv2_utils/layers/detector/hough_circle.py
cv2_utils/layers/thresholding/__init__.py
cv2_utils/layers/thresholding/hsv_filter.py
cv2_utils/layers/transform/__init__.py
cv2_utils/layers/transform/roi_selector.py